argument_tasks/__init__.py
argument_tasks/interface.py
argument_tasks/task.py
argument_tasks-0.1.dist-info/LICENSE.txt
argument_tasks-0.1.dist-info/METADATA
argument_tasks-0.1.dist-info/WHEEL
argument_tasks-0.1.dist-info/top_level.txt
argument_tasks-0.1.dist-info/RECORD
