Metadata-Version: 2.1
Name: argument-tasks
Version: 0.1
Summary: Tool to call tasks by arguments defined easily
Home-page: https://github.com/santiagoMeloMedina/argument-tasks
Author: Santiago Melo Medina
Author-email: smelomedina05@gmail.com
License: MIT
Download-URL: https://github.com/santiagoMeloMedina/argument-tasks/archive/refs/tags/0.1.zip
Keywords: Injection,Singleton,Simple
Platform: UNKNOWN
Classifier: Development Status :: 4 - Beta
Classifier: Intended Audience :: Developers
Classifier: Topic :: Software Development :: Build Tools
Classifier: License :: OSI Approved :: MIT License
Classifier: Programming Language :: Python :: 3.8
License-File: LICENSE.txt
Requires-Dist: pydantic (==1.8.2)
Requires-Dist: PyYAML (==6.0)
